stackit/stackitmarketplace/__init__.py
stackit/stackitmarketplace/api/__init__.py
stackit/stackitmarketplace/api/default_api.py
stackit/stackitmarketplace/api_client.py
stackit/stackitmarketplace/api_response.py
stackit/stackitmarketplace/configuration.py
stackit/stackitmarketplace/exceptions.py
stackit/stackitmarketplace/models/__init__.py
stackit/stackitmarketplace/models/approve_subscription_payload.py
stackit/stackitmarketplace/models/assets.py
stackit/stackitmarketplace/models/assets_end_user_license_agreement.py
stackit/stackitmarketplace/models/assets_product_description.py
stackit/stackitmarketplace/models/assets_service_level_agreement.py
stackit/stackitmarketplace/models/become_vendor.py
stackit/stackitmarketplace/models/catalog_pricing_option_highlight.py
stackit/stackitmarketplace/models/catalog_product_detail.py
stackit/stackitmarketplace/models/catalog_product_details_vendor.py
stackit/stackitmarketplace/models/catalog_product_facets_value_inner.py
stackit/stackitmarketplace/models/catalog_product_highlight.py
stackit/stackitmarketplace/models/catalog_product_overview.py
stackit/stackitmarketplace/models/catalog_product_overview_vendor.py
stackit/stackitmarketplace/models/catalog_product_pricing_option.py
stackit/stackitmarketplace/models/catalog_product_support_resource.py
stackit/stackitmarketplace/models/catalog_product_vendor_terms.py
stackit/stackitmarketplace/models/contact_sales.py
stackit/stackitmarketplace/models/delivery_method.py
stackit/stackitmarketplace/models/error_response.py
stackit/stackitmarketplace/models/free_trial.py
stackit/stackitmarketplace/models/inquiries_create_inquiry_payload.py
stackit/stackitmarketplace/models/inquiry_become_vendor.py
stackit/stackitmarketplace/models/inquiry_contact_sales.py
stackit/stackitmarketplace/models/inquiry_form_type.py
stackit/stackitmarketplace/models/inquiry_register_testing.py
stackit/stackitmarketplace/models/inquiry_request_private_plan.py
stackit_stackitmarketplace-1.16.0.dist-info/METADATA
stackit_stackitmarketplace-1.16.0.dist-info/WHEEL
stackit_stackitmarketplace-1.16.0.dist-info/licenses/LICENSE.md
stackit_stackitmarketplace-1.16.0.dist-info/licenses/NOTICE.txt
stackit_stackitmarketplace-1.16.0.dist-info/RECORD
